nomnom/__init__.py
nomnom/_version.py
nomnom/admin.py
nomnom/apps.py
nomnom/asgi.py
nomnom/celery.py
nomnom/convention.py
nomnom/middleware.py
nomnom/model_utils.py
nomnom/reporting.py
nomnom/test_settings.py
nomnom/test_urls.py
nomnom/wsgi.py
nomnom/advise/__init__.py
nomnom/advise/admin.py
nomnom/advise/apps.py
nomnom/advise/forms.py
nomnom/advise/models.py
nomnom/advise/receivers.py
nomnom/advise/tests.py
nomnom/advise/urls.py
nomnom/advise/views.py
nomnom/advise/migrations/0001_initial.py
nomnom/advise/migrations/0002_alter_proposal_options.py
nomnom/advise/migrations/0003_remove_proposal_vote_closes_at_and_more.py
nomnom/advise/migrations/0004_alter_proposal_state.py
nomnom/advise/migrations/__init__.py
nomnom/advise/static/css/advise.css
nomnom/advise/templates/admin/advise/proposal/change_form.html
nomnom/advise/templates/advise/_proposal_entry_desktop.html
nomnom/advise/templates/advise/_proposal_entry_mobile.html
nomnom/advise/templates/advise/index.html
nomnom/advise/templates/advise/vote.html
nomnom/advise/templatetags/advise_filters.py
nomnom/base/signals.py
nomnom/base/views.py
nomnom/base/static/images/nomnom-icon.png
nomnom/base/static/images/nomnom-logo.png
nomnom/base/templates/base.html
nomnom/base/templates/customize/convention_styles.html
nomnom/base/templates/nomnom/index.html
nomnom/canonicalize/__init__.py
nomnom/canonicalize/admin.py
nomnom/canonicalize/apps.py
nomnom/canonicalize/factories.py
nomnom/canonicalize/models.py
nomnom/canonicalize/receivers.py
nomnom/canonicalize/urls.py
nomnom/canonicalize/migrations/0001_initial.py
nomnom/canonicalize/migrations/0002_alter_work_nominations.py
nomnom/canonicalize/migrations/__init__.py
nomnom/canonicalize/templates/canonicalize/ballots.html
nomnom/canonicalize/templates/canonicalize/eph.html
nomnom/canonicalize/templates/canonicalize/bits/eph_step.html
nomnom/canonicalize/tests/__init__.py
nomnom/canonicalize/tests/conftest.py
nomnom/canonicalize/tests/test_admin.py
nomnom_hugoawards-2026.2.0.dist-info/METADATA
nomnom_hugoawards-2026.2.0.dist-info/WHEEL
nomnom_hugoawards-2026.2.0.dist-info/licenses/LICENSE
nomnom_hugoawards-2026.2.0.dist-info/RECORD
