Metadata-Version: 2.4
Name: nomnom-hugoawards
Version: 2026.2.0
Summary: The NomNom Hugo Awards voting package
Author-email: Chris Rose <offline@offby1.net>
Maintainer-email: Chris Rose <offline@offby1.net>
License: MIT
License-File: LICENSE
Classifier: Development Status :: 3 - Alpha
Classifier: License :: OSI Approved :: MIT License
Classifier: Programming Language :: Python :: 3.12
Classifier: Programming Language :: Python :: 3.13
Classifier: Typing :: Typed
Requires-Python: <3.14,>=3.12.0
Requires-Dist: boto3-stubs[s3]~=1.34
Requires-Dist: boto3~=1.34
Requires-Dist: botocore-stubs~=1.34
Requires-Dist: bs4~=0.0
Requires-Dist: celery~=5.3
Requires-Dist: django-admin-action-forms~=2.0
Requires-Dist: django-admin-autocomplete-filter~=0.7
Requires-Dist: django-bootstrap-static>=5.3.3
Requires-Dist: django-bootstrap5<25,~=23.3
Requires-Dist: django-browser-reload~=1.12
Requires-Dist: django-celery-beat~=2.5
Requires-Dist: django-celery-results~=2.5
Requires-Dist: django-click~=2.3
Requires-Dist: django-cors-headers~=4.3
Requires-Dist: django-extensions~=3.2
Requires-Dist: django-fsm~=2.8
Requires-Dist: django-google-fonts>=0.0.3
Requires-Dist: django-htmx~=1.17
Requires-Dist: django-ipware~=7.0
Requires-Dist: django-logentry-admin~=1.1
Requires-Dist: django-markdownfield~=0.11
Requires-Dist: django-markdownify~=0.9
Requires-Dist: django-model-utils~=5.0
Requires-Dist: django-oauth-toolkit~=3.0
Requires-Dist: django-render-block~=0.9
Requires-Dist: django-seed~=0.3
Requires-Dist: django-svcs~=0.3
Requires-Dist: django-watchman~=1.3
Requires-Dist: django~=5.1
Requires-Dist: environ-config~=24.1
Requires-Dist: flower~=2.0
Requires-Dist: fontawesomefree~=6.5
Requires-Dist: inflect>=7.5.0
Requires-Dist: jinja2~=3.1
Requires-Dist: psycopg[binary]
Requires-Dist: pyrankvote~=2.0
Requires-Dist: redis~=5.0
Requires-Dist: sentry-sdk[celery,django]~=2.19
Requires-Dist: social-auth-core~=4.5
Requires-Dist: svcs<26.0,>=24.1
Requires-Dist: whitenoise~=6.6
